volute_ppt/__init__.py
volute_ppt/__main__.py
volute_ppt/advanced_powerpoint_tools.py
volute_ppt/cli.py
volute_ppt/cloud_server.py
volute_ppt/config.py
volute_ppt/powerpoint_manager.py
volute_ppt/powerpoint_metadata.py
volute_ppt/powerpoint_tools.py
volute_ppt/ppt_server.py
volute_ppt/sdk.py
volute_ppt/server_local.py
volute_ppt/shape_editing_tools.py
volute_ppt/slide_capture_tools.py
volute_ppt/smart_text_processor.py
volute_ppt/toolkit.py
volute_ppt/powerpoint/__init__.py
volute_ppt/powerpoint/parser.py
volute_ppt/powerpoint/slide_executor.py
volute_ppt-1.4.6.dist-info/METADATA
volute_ppt-1.4.6.dist-info/WHEEL
volute_ppt-1.4.6.dist-info/entry_points.txt
volute_ppt-1.4.6.dist-info/top_level.txt
volute_ppt-1.4.6.dist-info/RECORD
