Metadata-Version: 2.4
Name: volute-ppt
Version: 1.4.6
Summary: Advanced MCP server for PowerPoint automation - comprehensive editing, analysis, and multimodal AI integration with intelligent text processing and native bullet conversion
Home-page: https://gitlab.com/coritan/volute-ppt
Author: Coritan
Author-email: Coritan <your-email@example.com>
License: MIT
Project-URL: Homepage, https://gitlab.com/coritan/volute-ppt
Project-URL: Repository, https://gitlab.com/coritan/volute-ppt.git
Project-URL: Issues, https://gitlab.com/coritan/volute-ppt/-/issues
Project-URL: Documentation, https://gitlab.com/coritan/volute-ppt/-/blob/main/DEVELOPER_GUIDE.md
Keywords: mcp,powerpoint,ai,agents,desktop,automation,com,multimodal,vision,slides,image-capture,text-editing,bullet-conversion,shape-editing,template-extraction,presentation-comparison
Classifier: Development Status :: 4 - Beta
Classifier: Intended Audience :: Developers
Classifier: License :: OSI Approved :: MIT License
Classifier: Operating System :: Microsoft :: Windows
Classifier: Programming Language :: Python :: 3
Classifier: Programming Language :: Python :: 3.8
Classifier: Programming Language :: Python :: 3.9
Classifier: Programming Language :: Python :: 3.10
Classifier: Programming Language :: Python :: 3.11
Classifier: Topic :: Software Development :: Libraries :: Python Modules
Classifier: Topic :: Office/Business :: Office Suites
Classifier: Topic :: Scientific/Engineering :: Artificial Intelligence
Requires-Python: >=3.8
Requires-Dist: fastmcp>=2.0.0
Requires-Dist: httpx>=0.25.0
Requires-Dist: python-dotenv>=1.0.0
Requires-Dist: pydantic>=2.0.0
Requires-Dist: python-pptx>=0.6.21
Requires-Dist: Pillow>=9.0.0
Requires-Dist: pywin32>=306; platform_system == "Windows"
Requires-Dist: langchain>=0.1.8
Provides-Extra: dev
Requires-Dist: pytest>=7.0.0; extra == "dev"
Requires-Dist: pytest-asyncio>=0.21.0; extra == "dev"
Requires-Dist: build>=0.10.0; extra == "dev"
Requires-Dist: twine>=4.0.0; extra == "dev"
Dynamic: author
Dynamic: home-page
Dynamic: requires-python
